setup.py
OneCube.egg-info/PKG-INFO
OneCube.egg-info/SOURCES.txt
OneCube.egg-info/dependency_links.txt
OneCube.egg-info/requires.txt
OneCube.egg-info/top_level.txt
onecube/__init__.py